pesviewer/__init__.py
pesviewer/pesviewer.py
PESViewer-1.1.dist-info/LICENSE
PESViewer-1.1.dist-info/METADATA
PESViewer-1.1.dist-info/WHEEL
PESViewer-1.1.dist-info/entry_points.txt
PESViewer-1.1.dist-info/top_level.txt
PESViewer-1.1.dist-info/RECORD
