Metadata-Version: 2.1
Name: PESViewer
Version: 1.1
Summary: Depiction of Potential Energy Surfaces.
Home-page: https://github.com/rubenvdvijver/PESViewer.git
Author: Ruben Van de Vijver
Author-email: vandevijver.ruben@gmail.com
License: MIT
Platform: UNKNOWN
Requires-Dist: matplotlib
Requires-Dist: numpy
